[
  {
    "email": "olivier@gmbs.fr",
    "password": "YhBgDu6nbr$l",
    "auth_user_id": "284a36c7-17eb-4132-9324-cdd00784ed3c",
    "name": "Olivier",
    "prenom": "Gestionnaire",
    "username": "olivier"
  },
  {
    "email": "badr@gmbs.fr",
    "password": "j3%LrGETb&Ud",
    "auth_user_id": "309a2027-59fe-4abb-a9b5-30ec7c26c0a4",
    "name": "Badr",
    "prenom": "Boujimal",
    "username": "badr"
  },
  {
    "email": "admin@gmbs.fr",
    "password": "zU$FromgNYZ0",
    "auth_user_id": "88408e36-338c-4b63-a403-79dd584467e5",
    "name": "Admin",
    "prenom": "Système",
    "username": "admin"
  },
  {
    "email": "andrea@gmbs.fr",
    "password": "$3MP@XTamhh&",
    "auth_user_id": "10deabb1-7205-4f0b-a6ea-75b666ace342",
    "name": "Andrea",
    "prenom": "GAUTRET",
    "username": "andrea"
  },
  {
    "email": "tom@gmbs.fr",
    "password": "cFdxukPhInqZ",
    "auth_user_id": "3af56815-1339-491a-a914-a8453eb28b0e",
    "name": "Tom",
    "prenom": "Birckel",
    "username": "tom"
  },
  {
    "email": "paul@gmbs.fr",
    "password": "k4&#GZLtX@cE",
    "auth_user_id": "584836ae-9fad-408c-8aba-e8eba7d55a32",
    "name": "Paul",
    "prenom": "Aguenana",
    "username": "paul"
  },
  {
    "email": "louis@gmbs.fr",
    "password": "kX!@uj3$FuTb",
    "auth_user_id": "c53f5531-f297-4753-861e-b2ae020b1ae6",
    "name": "Louis",
    "prenom": "Saune",
    "username": "louis"
  },
  {
    "email": "samuel@gmbs.fr",
    "password": "bF%V@RI82SM5",
    "auth_user_id": "71bd5ebc-0b52-4fb1-90c7-63b1c4288947",
    "name": "Samuel",
    "prenom": "s",
    "username": "samuel"
  },
  {
    "email": "lucien@gmbs.fr",
    "password": "mzF1bbOkttBZ",
    "auth_user_id": "77c789a0-aedb-4f0e-b90e-15aa8ea022bb",
    "name": "Lucien",
    "prenom": "L",
    "username": "lucien"
  },
  {
    "email": "killian@gmbs.fr",
    "password": "HI0hIzd5!lKj",
    "auth_user_id": "4bad22fd-74e0-4c68-b079-cf1f99b19568",
    "name": "Killian",
    "prenom": "K",
    "username": "killian"
  },
  {
    "email": "dimitri@gmbs.fr",
    "password": "sDW5DmHgQrwX",
    "auth_user_id": "b0621281-944e-4c77-ad31-1be054af31f4",
    "name": "Dimitri",
    "prenom": "Montanari",
    "username": "dimitri"
  }
]